{
	"variables": [],
	"info": {
		"name": "RentNFT",
		"_postman_id": "1b90de23-1a9c-a9c3-567d-da9d278f87b0",
		"description": "",
		"schema": "https://schema.getpostman.com/json/collection/v2.0.0/collection.json"
	},
	"item": [
		{
			"name": "mint",
			"request": {
				"url": "localhost:3000/api/mint",
				"method": "POST",
				"header": [
					{
						"key": "Content-Type",
						"value": "application/json",
						"description": ""
					}
				],
				"body": {
					"mode": "raw",
					"raw": "{\n\t\"tokenUri\":\"Hello\",\n\t\"address\":\"0x6fB251Aa440162e70e2956e36c188Fa49b4994CE\"\n}"
				},
				"description": ""
			},
			"response": []
		},
		{
			"name": "Isrent",
			"request": {
				"url": "localhost:3000/api/istenant",
				"method": "POST",
				"header": [
					{
						"key": "Content-Type",
						"value": "application/json",
						"description": ""
					}
				],
				"body": {
					"mode": "raw",
					"raw": "{\n\t\"tokenId\":\"21\",\n\t\"address\":\"0x6fB251Aa440162e70e2956e36c188Fa49b4994CE\"\n}"
				},
				"description": ""
			},
			"response": []
		},
		{
			"name": "RentNFT",
			"request": {
				"url": "localhost:3000/api/rentnft",
				"method": "POST",
				"header": [
					{
						"key": "Content-Type",
						"value": "application/json",
						"description": ""
					}
				],
				"body": {
					"mode": "raw",
					"raw": "{\n\t\"tokenId\":\"21\",\n\t\"address\":\"0x6fB251Aa440162e70e2956e36c188Fa49b4994CE\"\n}"
				},
				"description": ""
			},
			"response": []
		},
		{
			"name": "CheckBalanceOfAddress",
			"request": {
				"url": "localhost:3000/api/balanceOf",
				"method": "POST",
				"header": [],
				"body": {},
				"description": ""
			},
			"response": []
		},
		{
			"name": "CheckTenant",
			"request": {
				"url": "localhost:3000/api/isTenant",
				"method": "POST",
				"header": [],
				"body": {},
				"description": ""
			},
			"response": []
		},
		{
			"name": "TokenName",
			"request": {
				"url": "localhost:3000/api/name",
				"method": "POST",
				"header": [],
				"body": {},
				"description": ""
			},
			"response": []
		},
		{
			"name": "OwnerOfContract",
			"request": {
				"url": "localhost:3000/api/owner",
				"method": "POST",
				"header": [],
				"body": {},
				"description": ""
			},
			"response": []
		},
		{
			"name": "CheckPaused",
			"request": {
				"url": "localhost:3000/api/paused",
				"method": "POST",
				"header": [],
				"body": {},
				"description": ""
			},
			"response": []
		},
		{
			"name": "TokenSymbol",
			"request": {
				"url": "localhost:3000/api/symbol",
				"method": "POST",
				"header": [],
				"body": {},
				"description": ""
			},
			"response": []
		},
		{
			"name": "tokenUri",
			"request": {
				"url": "localhost:3000/api/tokenURI",
				"method": "POST",
				"header": [
					{
						"key": "Content-Type",
						"value": "application/json",
						"description": ""
					}
				],
				"body": {
					"mode": "raw",
					"raw": ""
				},
				"description": ""
			},
			"response": []
		},
		{
			"name": "Approve",
			"request": {
				"url": "localhost:3000/api/approve",
				"method": "POST",
				"header": [
					{
						"key": "Content-Type",
						"value": "application/json",
						"description": ""
					}
				],
				"body": {
					"mode": "raw",
					"raw": ""
				},
				"description": ""
			},
			"response": []
		},
		{
			"name": "RemoveTenant",
			"request": {
				"url": "localhost:3000/api/removetenant",
				"method": "POST",
				"header": [
					{
						"key": "Content-Type",
						"value": "application/json",
						"description": ""
					}
				],
				"body": {
					"mode": "raw",
					"raw": ""
				},
				"description": ""
			},
			"response": []
		},
		{
			"name": "TransferFrom",
			"request": {
				"url": "localhost:3000/api/transferFrom",
				"method": "POST",
				"header": [
					{
						"key": "Content-Type",
						"value": "application/json",
						"description": ""
					}
				],
				"body": {
					"mode": "raw",
					"raw": ""
				},
				"description": ""
			},
			"response": []
		},
		{
			"name": "OwnerOfToken",
			"request": {
				"url": "localhost:3000/api/ownerof",
				"method": "POST",
				"header": [
					{
						"key": "Content-Type",
						"value": "application/json",
						"description": ""
					}
				],
				"body": {
					"mode": "raw",
					"raw": ""
				},
				"description": ""
			},
			"response": []
		},
		{
			"name": "IsApprovedForAll",
			"request": {
				"url": "localhost:3000/api/isapprovedforall",
				"method": "POST",
				"header": [
					{
						"key": "Content-Type",
						"value": "application/json",
						"description": ""
					}
				],
				"body": {
					"mode": "raw",
					"raw": ""
				},
				"description": ""
			},
			"response": []
		},
		{
			"name": "GetApproved",
			"request": {
				"url": "localhost:3000/api/getapproved",
				"method": "POST",
				"header": [
					{
						"key": "Content-Type",
						"value": "application/json",
						"description": ""
					}
				],
				"body": {
					"mode": "raw",
					"raw": ""
				},
				"description": ""
			},
			"response": []
		},
		{
			"name": "SetApprovalForAll",
			"request": {
				"url": "localhost:3000/api/setapprovalforall",
				"method": "POST",
				"header": [
					{
						"key": "Content-Type",
						"value": "application/json",
						"description": ""
					}
				],
				"body": {
					"mode": "raw",
					"raw": ""
				},
				"description": ""
			},
			"response": []
		}
	]
}